selectel_storage/__init__.py
selectel_storage/exceptions.py
selectel_storage/flask.py
selectel_storage/base/__init__.py
selectel_storage/base/mongoengine.py
selectel_storage/base/storage.py
selectel_storage-0.0.26.dist-info/METADATA
selectel_storage-0.0.26.dist-info/WHEEL
selectel_storage-0.0.26.dist-info/top_level.txt
selectel_storage-0.0.26.dist-info/RECORD
