Metadata-Version: 2.1
Name: selectel-storage
Version: 0.0.26
Summary: UNKNOWN
Home-page: https://github.com/KokocGroup/selectel_storage
Author: UNKNOWN
Author-email: UNKNOWN
License: UNKNOWN
Download-URL: https://github.com/KokocGroup/selectel_storage/tarball/v0.0.26
Platform: UNKNOWN
Requires-Dist: mongoengine (==0.10.0)
Requires-Dist: python-magic (==0.4.10)
Requires-Dist: requests (==2.10.0)
